cdk_cloudformation_netapp_fsxn_snapmirror/__init__.py
cdk_cloudformation_netapp_fsxn_snapmirror/py.typed
cdk_cloudformation_netapp_fsxn_snapmirror/_jsii/__init__.py
cdk_cloudformation_netapp_fsxn_snapmirror/_jsii/netapp-fsxn-snapmirror@1.3.0-alpha.7.jsii.tgz
cdk_cloudformation_netapp_fsxn_snapmirror-1.3.0a7.dist-info/LICENSE
cdk_cloudformation_netapp_fsxn_snapmirror-1.3.0a7.dist-info/METADATA
cdk_cloudformation_netapp_fsxn_snapmirror-1.3.0a7.dist-info/WHEEL
cdk_cloudformation_netapp_fsxn_snapmirror-1.3.0a7.dist-info/top_level.txt
cdk_cloudformation_netapp_fsxn_snapmirror-1.3.0a7.dist-info/RECORD
